{
    "privacy": "ግለሰቦች",
    "login": "ግባ",
    "logout": "ውጣ",
    "signup": "መመዝገብ",
    "loginToYourAccount": "ወደ መለያዎት ግባ",
    "createYourAccount": "መለያዎትን ይፍጠሩ",
    "forgotPassword": "የይለፍ ቃል እንደርስ?",
    "password": "የይለፍ ቃል",
    "phoneNumber": "የስልክ ቁጥር",
    "email": "ኢሜይል",
    "haveNoAccount": "መለያ የለዎትም?",
    "haveAccount": "የቀድሞ መለያ አለዎት?",
    "confirmPassword": "የይለፍ ቃል ይረጋገጡ",
    "resetYourPassword": "የይለፍ ቃል ይዘርዝሩ",
    "sendResetLink": "የዘርዝር አገናኝ ይላኩ",
    "back": "ወደ ኋላ",
    "home": "መነሻ",
    "about": "ስለ",
    "services": "አገልግሎቶች",
    "contact": "እውቅና",
    "register": "መመዝገብ",
    "headerTitle": "የዶሮ እንቁላል እንደምንግደዋ",
    "headerSubtitle": "የዶሮ እንቁላል አስተዳደር ይዘው",
    "headerDescription": "የተለዋዋጭ ሶፍትዌር መፍትሄዎች ለየእንቁላል አስተዳደር.",
    "exploreFeaturesButton": "የተለዋዋጭ ይመልከቱ",
    "welcomeTitle": "ወደ ዶሮSAAS ይቀበሉ!",
    "welcomeDescription": "በዶሮSAS የዶሮ እንቁላል እንደምንግደዋ እንደምንግደዋ ለየእንቁላል አስተዳደር ይዘው ወቅታዊ ሶፍትዌር መፍትሄዎች እንደምንግደዋ.",
    "welcomeDetails": "መድረክ እንቁላል ይዘው ይህ እንደምንግደዋ የሚፈለጉ መሳሪያዎች ላይ ይታወቃሉ.",
    "trustedByStatistic": "42",
    "trustedByDescription": "የእንቁላል እንደምንግደዋ ይታወቃሉ",
    "offeringsTitle": "ምንዛሬ ነን",
    "offeringsItem1": "የዶሮ እንቁላል አስተዳደር ሶፍትዌር: የወንጌል ጤና እና መረጃ መለያዎች.",
    "offeringsItem2": "ውሂብ ተመልከቢ: እንቁላል እንደምንግደዋ ይሁን.",
    "offeringsItem3": "የክርስቲና አስተዳደር: ወደ ይገኙ ይሁን.",
    "offeringsItem4": "ደንበኛ ድጋፍ: የምንገናኝ ቡድን ይገኙ ይሁን.",
    "productsTitle": "የእንቁላል ዝርዝር",
    "productsDescription": "የዶሮ እንቁላል ዝርዝር ይታወቃሉ.",
    "productBrownEggsTitle": "ቡሩን እንቁላል",
    "productBrownEggsDescription": "የተፈጥሮ እንቁላል እንደ ወንጌል.",
    "productLittleChicksTitle": "ትንሽ ድንጋይ",
    "productLittleChicksDescription": "እንደምንግደዋ ይሁን.",
    "productFreshChickenTitle": "አዲስ ዶሮ",
    "productFreshChickenDescription": "የተፈጥሮ እንቁላል እንደ ወንጌል.",
    "productWhiteEggsTitle": "ነጭ እንቁላል",
    "productWhiteEggsDescription": "የተፈጥሮ እንቁላል ይሁን.",
    "error": "ስህተት",
    "contactUsTitle": "እንቁላል ይገኙ",
    "contactUsDescription": "እንቁላል ይገኙ ይደርሱ!",
    "contactFormName": "ስም",
    "contactFormMessage": "መልእክትዎ",
    "contactFormSendMessage": "መልእክት ይላኩ",
    "contactInfoTitle": "የእንቁላል እንደምንግደዋ",
    "contactInfoEmail": "ኢሜይል: poultry@gmail.com",
    "contactInfoPhone": "ስልክ: +251 968 991 888",
    "contactInfoAddress": "አድራሻ: አዲስ አበባ, ኢትዮጵያ",
    "followUs": "እንቁላል ይገኙ",
    "aboutUsTitle": "ስለ እኛ",
    "aboutUsDescription": "የምንገናኝ ቡድን ይገኙ.",
    "quickLinksTitle": "ፈጣን የመዳረሻ",
    "quickLink1": "አገልግሎቶች",
    "quickLink2": "ስለ እኛ",
    "quickLink3": "እንቁላል ይገኙ",
    "quickLink4": "የነሱ ጥያቄዎች",
    "footerFollowUs": "እንቁላል ይገኙ",
    "footerCopyright": "© 2024 የእንቁላል እንደምንግደዋ"
}